decodex/__init__.py
decodex/__main__.py
decodex/constant/__init__.py
decodex/constant/fs.py
decodex/convert/__init__.py
decodex/convert/address/__init__.py
decodex/convert/address/tagger.py
decodex/convert/signature/__init__.py
decodex/convert/signature/signature.py
decodex/convert/token/__init__.py
decodex/convert/token/erc20.py
decodex/decode/__init__.py
decodex/decode/decode.py
decodex/exceptions/__init__.py
decodex/installer/__init__.py
decodex/installer/callbacks.py
decodex/installer/installer.py
decodex/installer/utils.py
decodex/search/README.md
decodex/search/__init__.py
decodex/search/searcher.py
decodex/translate/__init__.py
decodex/translate/events/__init__.py
decodex/translate/events/dex.py
decodex/translate/events/lending.py
decodex/translate/events/tokens.py
decodex/translate/translate.py
decodex/type/__init__.py
decodex/type/action_type.py
decodex/type/base.py
decodex/type/rpc_type.py
decodex/type/tx_type.py
decodex/utils/__init__.py
decodex/utils/fmt.py
decodex/utils/utils.py
decodex-0.5.11.dist-info/METADATA
decodex-0.5.11.dist-info/WHEEL
decodex-0.5.11.dist-info/entry_points.txt
decodex-0.5.11.dist-info/RECORD
